plex_formatter/__init__.py
plex_formatter/plex_rename.py
Plex_TV_Show_File_Formatter-1.0.4.dist-info/LICENSE
Plex_TV_Show_File_Formatter-1.0.4.dist-info/METADATA
Plex_TV_Show_File_Formatter-1.0.4.dist-info/WHEEL
Plex_TV_Show_File_Formatter-1.0.4.dist-info/entry_points.txt
Plex_TV_Show_File_Formatter-1.0.4.dist-info/top_level.txt
Plex_TV_Show_File_Formatter-1.0.4.dist-info/RECORD
