Metadata-Version: 2.1
Name: Plex-TV-Show-File-Formatter
Version: 1.0.4
Summary: Renames an orded directory of a TV season into Plexs' preferred format
Home-page: https://github.com/matthewkayne/Plex-TV-Show-File-Formatter
Author: Matthew Kayne
Author-email: matthewkayne2004@gmail.com
License: UNKNOWN
Platform: UNKNOWN
Requires-Python: >=3.7
License-File: LICENSE
